clip_master/__init__.py
clip_master/__main__.py
clip_master/cli.py
clip_master/config.py
clip_master/core.py
clip_master/gui.py
clip_master/utils.py
clip_master/workers.py
clip_master/resources/icon2.png
clip_master_toolkit-0.2.5.dist-info/METADATA
clip_master_toolkit-0.2.5.dist-info/WHEEL
clip_master_toolkit-0.2.5.dist-info/entry_points.txt
clip_master_toolkit-0.2.5.dist-info/top_level.txt
clip_master_toolkit-0.2.5.dist-info/RECORD
