Metadata-Version: 2.1
Name: clip-master-toolkit
Version: 0.2.5
Summary: A comprehensive clipboard management toolkit with GUI and CLI interfaces
Home-page: https://github.com/Sunwood-ai-labs/ClipMaster
Author: Sunwood-ai-labs
Author-email: sunwood.ai.labs@gmail.com
Classifier: Programming Language :: Python :: 3
Classifier: License :: OSI Approved :: MIT License
Classifier: Operating System :: OS Independent
Requires-Python: >=3.6
Requires-Dist: PyQt6
Requires-Dist: pyperclip
Requires-Dist: litellm
Requires-Dist: qt-material
Requires-Dist: loguru
